scageclock/__init__.py
scageclock/cli.py
scageclock/dataloader.py
scageclock/evaluation.py
scageclock/formatting.py
scageclock/h5ad_dataloader.py
scageclock/h5ad_sampler.py
scageclock/model/CatBoost.py
scageclock/model/GatedMultiheadAttention.py
scageclock/model/Linear.py
scageclock/model/MLP.py
scageclock/model/XGBoost.py
scageclock/prepare_inputs.py
scageclock/scAgeClock.py
scageclock/utility.py
scageclock/visualization.py
scageclock-0.1.3.dist-info/LICENSE
scageclock-0.1.3.dist-info/METADATA
scageclock-0.1.3.dist-info/WHEEL
scageclock-0.1.3.dist-info/entry_points.txt
scageclock-0.1.3.dist-info/RECORD
