Metadata-Version: 2.1
Name: scageclock
Version: 0.1.3
Summary: scAgeClock: a single-cell transcriptome based human aging clock model using gated multi-head attention neural networks
Home-page: https://github.com/gangcai/scageclock
Author: Gangcai Xie
Author-email: gcxiester@gmail.com> or <gangcai@ntu.edu.cn
Requires-Python: >=3.12,<4.0
Classifier: Programming Language :: Python :: 3
Classifier: Programming Language :: Python :: 3.12
Requires-Dist: catboost (>=1.2.7,<1.3.0)
Requires-Dist: matplotlib (>=3.9.2,<3.10.0)
Requires-Dist: numpy (>=1.26.4,<1.27.0)
Requires-Dist: openpyxl (>=3.1.5,<3.2.0)
Requires-Dist: pandas (>=2.2.2,<2.3.0)
Requires-Dist: pyarrow (>=20.0.0,<20.1.0)
Requires-Dist: scanpy (>=1.10.4,<1.11.0)
Requires-Dist: torch (>=2.6.0,<2.7.0)
Requires-Dist: xgboost (>=2.1.2,<2.2.0)
Project-URL: Repository, https://github.com/gangcai/scageclock
